MANIFEST.in
README
requirements.txt
setup.py
ajenti.plugin.fstab.egg-info/PKG-INFO
ajenti.plugin.fstab.egg-info/SOURCES.txt
ajenti.plugin.fstab.egg-info/dependency_links.txt
ajenti.plugin.fstab.egg-info/top_level.txt
ajenti_plugin_fstab/.gitignore
ajenti_plugin_fstab/README.md
ajenti_plugin_fstab/__init__.py
ajenti_plugin_fstab/main.py
ajenti_plugin_fstab/plugin.yml
ajenti_plugin_fstab/requirements.txt
ajenti_plugin_fstab/views.py
ajenti_plugin_fstab/locale/af/LC_MESSAGES/app.js
ajenti_plugin_fstab/locale/af/LC_MESSAGES/app.po
ajenti_plugin_fstab/locale/ar/LC_MESSAGES/app.js
ajenti_plugin_fstab/locale/ar/LC_MESSAGES/app.po
ajenti_plugin_fstab/locale/be/LC_MESSAGES/app.js
ajenti_plugin_fstab/locale/be/LC_MESSAGES/app.po
ajenti_plugin_fstab/locale/bg/LC_MESSAGES/app.js
ajenti_plugin_fstab/locale/bg/LC_MESSAGES/app.po
ajenti_plugin_fstab/locale/bn/LC_MESSAGES/app.js
ajenti_plugin_fstab/locale/bn/LC_MESSAGES/app.po
ajenti_plugin_fstab/locale/bs/LC_MESSAGES/app.js
ajenti_plugin_fstab/locale/bs/LC_MESSAGES/app.po
ajenti_plugin_fstab/locale/ca/LC_MESSAGES/app.js
ajenti_plugin_fstab/locale/ca/LC_MESSAGES/app.po
ajenti_plugin_fstab/locale/cs/LC_MESSAGES/app.js
ajenti_plugin_fstab/locale/cs/LC_MESSAGES/app.po
ajenti_plugin_fstab/locale/da/LC_MESSAGES/app.js
ajenti_plugin_fstab/locale/da/LC_MESSAGES/app.po
ajenti_plugin_fstab/locale/de/LC_MESSAGES/app.js
ajenti_plugin_fstab/locale/de/LC_MESSAGES/app.po
ajenti_plugin_fstab/locale/el/LC_MESSAGES/app.js
ajenti_plugin_fstab/locale/el/LC_MESSAGES/app.po
ajenti_plugin_fstab/locale/en/LC_MESSAGES/app.po
ajenti_plugin_fstab/locale/eo/LC_MESSAGES/app.js
ajenti_plugin_fstab/locale/eo/LC_MESSAGES/app.po
ajenti_plugin_fstab/locale/es-ES/LC_MESSAGES/app.js
ajenti_plugin_fstab/locale/es-ES/LC_MESSAGES/app.po
ajenti_plugin_fstab/locale/et/LC_MESSAGES/app.js
ajenti_plugin_fstab/locale/et/LC_MESSAGES/app.po
ajenti_plugin_fstab/locale/fa/LC_MESSAGES/app.js
ajenti_plugin_fstab/locale/fa/LC_MESSAGES/app.po
ajenti_plugin_fstab/locale/fi/LC_MESSAGES/app.js
ajenti_plugin_fstab/locale/fi/LC_MESSAGES/app.po
ajenti_plugin_fstab/locale/fr/LC_MESSAGES/app.js
ajenti_plugin_fstab/locale/fr/LC_MESSAGES/app.po
