Metadata-Version: 1.2
Name: ajenti.plugin.fstab
Version: 0.4
Summary: Fstab
Home-page: https://ajenti.org
Author: Arnaud Kientz
Author-email: arnaud@linuxmuster.net
License: UNKNOWN
Platform: UNKNOWN
Requires-Python: >=3
